url_to_calibre/__init__.py
url_to_calibre/main.py
url_to_calibre-1.0.0.dist-info/LICENSE.md
url_to_calibre-1.0.0.dist-info/METADATA
url_to_calibre-1.0.0.dist-info/WHEEL
url_to_calibre-1.0.0.dist-info/entry_points.txt
url_to_calibre-1.0.0.dist-info/RECORD
