Metadata-Version: 2.1
Name: url-to-calibre
Version: 1.0.0
Summary: Convert a URL's contents into ebook format and add to Calibre library
Author: alexcg
Requires-Python: >=3.9,<4.0
Classifier: Programming Language :: Python :: 3
Classifier: Programming Language :: Python :: 3.9
Classifier: Programming Language :: Python :: 3.10
Classifier: Programming Language :: Python :: 3.11
Classifier: Programming Language :: Python :: 3.12
Requires-Dist: beautifulsoup4 (>=4.13.1,<5.0.0)
Requires-Dist: ebooklib (>=0.18,<0.19)
Requires-Dist: lxml-html-clean (>=0.4.1,<0.5.0)
Requires-Dist: newspaper3k (>=0.2.8,<0.3.0)
